figma_compose/__init__.py
figma_compose/__main__.py
figma_compose/figmaToComposeMCP.py
figma_compose/prompt.txt
figma_to_compose_mcp-1.1.1.dist-info/METADATA
figma_to_compose_mcp-1.1.1.dist-info/WHEEL
figma_to_compose_mcp-1.1.1.dist-info/entry_points.txt
figma_to_compose_mcp-1.1.1.dist-info/top_level.txt
figma_to_compose_mcp-1.1.1.dist-info/RECORD
