Metadata-Version: 2.4
Name: figma-to-compose-mcp
Version: 1.1.1
Summary: A Model Context Protocol (MCP) server for generating Jetpack Compose code from Figma nodes.
Author-email: Manish Malviya <manish026@live.com>
Requires-Python: >=3.13
Requires-Dist: build>=1.2.2.post1
Requires-Dist: fastmcp==2.6.1
Requires-Dist: mcp[cli]>=1.9.4
Requires-Dist: requests>=2.28.0
Requires-Dist: twine>=6.1.0
Requires-Dist: mixpanel
